LICENSE
MANIFEST.in
README.rst
VERSION
requirements.txt
setup.py
unicore/__init__.py
unicore/__init__.pyc
unicore.ask.egg-info/PKG-INFO
unicore.ask.egg-info/SOURCES.txt
unicore.ask.egg-info/dependency_links.txt
unicore.ask.egg-info/entry_points.txt
unicore.ask.egg-info/namespace_packages.txt
unicore.ask.egg-info/not-zip-safe
unicore.ask.egg-info/requires.txt
unicore.ask.egg-info/top_level.txt
unicore/ask/__init__.py
unicore/ask/__init__.pyc
unicore/ask/service/__init__.py
unicore/ask/service/__init__.pyc
unicore/ask/service/models.py
unicore/ask/service/models.pyc
unicore/ask/service/questions_api.py
unicore/ask/service/questions_api.pyc
unicore/ask/service/schema.py
unicore/ask/service/schema.pyc
unicore/ask/service/validators.py
unicore/ask/service/validators.pyc
unicore/ask/service/alembic/README
unicore/ask/service/alembic/env.py
unicore/ask/service/alembic/env.pyc
unicore/ask/service/alembic/script.py.mako
unicore/ask/service/alembic/versions/11ec5eb390f4_initial.py
unicore/ask/service/alembic/versions/11ec5eb390f4_initial.pyc
unicore/ask/service/alembic/versions/2a4397511296_add_response_count_field.py
unicore/ask/service/alembic/versions/2a4397511296_add_response_count_field.pyc
unicore/ask/service/tests/__init__.py
unicore/ask/service/tests/__init__.pyc
unicore/ask/service/tests/test.ini
unicore/ask/service/tests/test_question_api.py
unicore/ask/service/tests/unicoreask_test.sqlite
unicore/ask/service/tests/__pycache__/test_question_api.cpython-27-PYTEST.pyc