Metadata-Version: 1.1
Name: unicore.ask
Version: 0.1.0
Summary: Universal Core REST service for Questions and Surveys.
Home-page: https://github.com/universalcore/unicore.ask.git
Author: Praekelt Foundation
Author-email: dev@praekelt.com
License: BSD
Keywords: question,survey,poll,universal,core
Platform: UNKNOWN
Classifier: Programming Language :: Python
Classifier: Framework :: Pyramid
Classifier: Topic :: Internet :: WWW/HTTP
Classifier: Topic :: Internet :: WWW/HTTP :: WSGI :: Application
